kinto_amo/__init__.py
kinto_amo/utils.py
kinto_amo/tests/__init__.py
kinto_amo/tests/config.ini
kinto_amo/tests/fixtures.json
kinto_amo/tests/support.py
kinto_amo/tests/test_plugin_setup.py
kinto_amo/tests/test_utils.py
kinto_amo/tests/test_views.py
kinto_amo/views/__init__.py
kinto_amo/views/services.py
kinto_amo-1.0.1.dist-info/DESCRIPTION.rst
kinto_amo-1.0.1.dist-info/METADATA
kinto_amo-1.0.1.dist-info/RECORD
kinto_amo-1.0.1.dist-info/WHEEL
kinto_amo-1.0.1.dist-info/metadata.json
kinto_amo-1.0.1.dist-info/top_level.txt
