Metadata-Version: 2.0
Name: kinto-amo
Version: 1.0.1
Summary: AMO-style routing for Kinto - with XML
Home-page: https://github.com/mozilla-services/kinto-amo
Author: Mozilla
Author-email: kinto@mozilla.org
License: Apache License (2.0)
Keywords: kinto
Platform: UNKNOWN
Classifier: Development Status :: 5 - Production/Stable
Classifier: Intended Audience :: Developers
Classifier: License :: OSI Approved :: Apache Software License
Classifier: Natural Language :: English
Classifier: Programming Language :: Python :: 2
Classifier: Programming Language :: Python :: 2.7
Classifier: Programming Language :: Python :: 3
Classifier: Programming Language :: Python :: 3.4
Requires-Dist: amo2kinto (>=3.2.0)
Requires-Dist: kinto (>=4.0.0)
